README.md
setup.py
test/__init__.py
test/__main__.py
test/_test_case.py
test/test_errors.py
test/test_grammar_construction.py
test/test_grammar_parsing.py
test/test_tokenizer.py
test/test_tokex.py
tokex/__init__.py
tokex/errors.py
tokex/functions.py
tokex/logger.py
tokex/tokex_class.py
tokex/utils.py
tokex.egg-info/PKG-INFO
tokex.egg-info/SOURCES.txt
tokex.egg-info/dependency_links.txt
tokex.egg-info/top_level.txt
tokex/grammar/__init__.py
tokex/grammar/flags.py
tokex/grammar/parse.py
tokex/grammar/elements/__init__.py
tokex/grammar/elements/_base_element.py
tokex/grammar/elements/scoped.py
tokex/grammar/elements/singular.py
tokex/grammar/elements/sub_grammar.py
tokex/tokenizers/__init__.py
tokex/tokenizers/tokenizer.py