Metadata-Version: 2.1
Name: tokex
Version: 2.1.0
Summary: String tokenizing and parsing library
Home-page: https://github.com/warrenspe/tokex
Author: Warren Spencer
Author-email: warrenspencer27@gmail.com
License: UNKNOWN
Keywords: tokex,tokenize,parse
Platform: UNKNOWN
Classifier: Development Status :: 5 - Production/Stable
Classifier: License :: OSI Approved :: MIT License
Classifier: Operating System :: OS Independent
Classifier: Programming Language :: Python
Classifier: Programming Language :: Python :: 2
Classifier: Programming Language :: Python :: 2.7
Classifier: Programming Language :: Python :: 3
Classifier: Programming Language :: Python :: 3.6
Classifier: Programming Language :: Python :: 3.7
Classifier: Programming Language :: Python :: 3.8
Classifier: Topic :: Software Development :: Libraries
Classifier: Topic :: Text Processing
